bd_jojo_mcp/__init__.py
bd_jojo_mcp/basic_tool.py
bd_jojo_mcp/mcp_client.py
bd_jojo_mcp/mcp_server.py
bd_jojo_mcp-0.1.7.dist-info/METADATA
bd_jojo_mcp-0.1.7.dist-info/WHEEL
bd_jojo_mcp-0.1.7.dist-info/entry_points.txt
bd_jojo_mcp-0.1.7.dist-info/top_level.txt
bd_jojo_mcp-0.1.7.dist-info/RECORD
