Metadata-Version: 2.4
Name: bd-jojo-mcp
Version: 0.1.7
Summary: Test Bytedance JoJo Basic MCP
Requires-Python: >=3.12
Requires-Dist: mcp>=1.12.4
Requires-Dist: pytz>=2025.2
